TOF_SIMS/__init__.py
TOF_SIMS/analysis.py
TOF_SIMS/clustering.py
TOF_SIMS/multivariate_analysis.py
TOF_SIMS/tof_sims_class.py
TOF_SIMS-1.1.0.dist-info/LICENCE
TOF_SIMS-1.1.0.dist-info/METADATA
TOF_SIMS-1.1.0.dist-info/WHEEL
TOF_SIMS-1.1.0.dist-info/top_level.txt
TOF_SIMS-1.1.0.dist-info/RECORD
