Metadata-Version: 2.1
Name: TOF-SIMS
Version: 1.1.0
Summary: Open and process 3D datasets generated by TESCAN FERA Xe plasma FIB-SEM with ToF-SIMS microscopes
Home-page: https://github.com/Remi-Branco/TOF-SIMS-package
Author: Remi Branco, Daniel Oldfield
Author-email: remi.branco@hotmail.fr, daniel.thomas.oldfield@gmail.com
License: UNKNOWN
Platform: UNKNOWN
Classifier: Programming Language :: Python :: 3
Classifier: License :: OSI Approved :: GNU General Public License v3 (GPLv3)
Classifier: Operating System :: OS Independent
Classifier: Development Status :: 5 - Production/Stable
Classifier: Framework :: IPython
Classifier: Intended Audience :: Science/Research
Classifier: Natural Language :: English
Classifier: Topic :: Scientific/Engineering :: Artificial Intelligence
Requires-Python: >=3.6
